{
    "parent": "item/generated",
    "textures": {
        "layer0": "deadlyworld:items/dirt_clump"
    },
    "display": 
    {
        "thirdperson_righthand": 
        {
            "rotation": [ 0, 0, 0 ],
            "translation": [ 0, 0, 0 ],
            "scale": [ 0.5, 0.5, 0.5 ]
        },
        "firstperson_righthand": 
        {
             "rotation": [ 0, 0, 0 ],
            "translation": [ 0, 0, 0 ],
            "scale": [ 0.5, 0.5, 0.5 ]
        },
        "thirdperson_lefthand": 
        {
            "rotation": [ 0, 0, 0 ],
            "translation": [ 0, 0, 0 ],
            "scale": [ 0.5, 0.5, 0.5 ]
        },
        "firstperson_lefthand": 
        {
             "rotation": [ 0, 0, 0 ],
            "translation": [ 0, 0, 0 ],
            "scale": [ 0.5, 0.5, 0.5 ]
        },
        "gui": 
        {
            "rotation": [ 0, 0, 0 ],
            "translation": [ 0, 0, 0 ],
            "scale": [ 0.5, 0.5, 0.5 ]
        },
        "ground": 
        {
            "rotation": [ 0, 0, 0 ],
            "translation": [ 0, 0, 0 ],
            "scale": [ 0.25, 0.25, 0.25 ]
        } 
    }
}